fastboot_log_parser.py
fastboot_log_parser-0.1.0.dist-info/LICENSE
fastboot_log_parser-0.1.0.dist-info/METADATA
fastboot_log_parser-0.1.0.dist-info/WHEEL
fastboot_log_parser-0.1.0.dist-info/top_level.txt
fastboot_log_parser-0.1.0.dist-info/RECORD
