Metadata-Version: 2.1
Name: fastboot_log_parser
Version: 0.1.0
Summary: A parser for Fastboot logs
Home-page: https://gitlab.com/mediatek/aiot/bsp/fastboot-log-parser
Author: Macpaul Lin
Author-email: macpaul.lin@mediatek.com
Classifier: Programming Language :: Python :: 3
Classifier: License :: OSI Approved :: MIT License
Classifier: Operating System :: OS Independent
Requires-Python: >=3.6
License-File: LICENSE
Requires-Dist: simplejson
